cdt/__init__.py
cdt/metrics.py
cdt/causality/__init__.py
cdt/causality/graph/CAM.py
cdt/causality/graph/CCDr.py
cdt/causality/graph/CGNN.py
cdt/causality/graph/GES.py
cdt/causality/graph/GIES.py
cdt/causality/graph/LiNGAM.py
cdt/causality/graph/PC.py
cdt/causality/graph/SAM.py
cdt/causality/graph/SAMv1.py
cdt/causality/graph/__init__.py
cdt/causality/graph/bnlearn.py
cdt/causality/graph/model.py
cdt/causality/graph/R_templates/CCDr.R
cdt/causality/graph/R_templates/bnlearn.R
cdt/causality/graph/R_templates/cam.R
cdt/causality/graph/R_templates/ges.R
cdt/causality/graph/R_templates/gies.R
cdt/causality/graph/R_templates/lingam.R
cdt/causality/graph/R_templates/pc.R
cdt/causality/pairwise/ANM.py
cdt/causality/pairwise/Bivariate_fit.py
cdt/causality/pairwise/CDS.py
cdt/causality/pairwise/GNN.py
cdt/causality/pairwise/IGCI.py
cdt/causality/pairwise/Jarfo.py
cdt/causality/pairwise/NCC.py
cdt/causality/pairwise/RCC.py
cdt/causality/pairwise/RECI.py
cdt/causality/pairwise/__init__.py
cdt/causality/pairwise/model.py
cdt/causality/pairwise/Jarfo_model/__init__.py
cdt/causality/pairwise/Jarfo_model/estimator.py
cdt/causality/pairwise/Jarfo_model/features.py
cdt/causality/pairwise/Jarfo_model/hsic.py
cdt/causality/pairwise/Jarfo_model/train.py
cdt/causality/pairwise/Jarfo_model/util.py
cdt/data/__init__.py
cdt/data/acyclic_graph_generator.py
cdt/data/causal_mechanisms.py
cdt/data/causal_pair_generator.py
cdt/data/loader.py
cdt/data/resources/Tuebingen_pairs.csv
cdt/data/resources/Tuebingen_targets.csv
cdt/data/resources/cyto_full_data.csv
cdt/data/resources/cyto_full_target.csv
cdt/data/resources/goldstandard_insilico100_multifactorial_1.csv
cdt/data/resources/goldstandard_insilico100_multifactorial_2.csv
cdt/data/resources/goldstandard_insilico100_multifactorial_3.csv
cdt/data/resources/goldstandard_insilico100_multifactorial_4.csv
cdt/data/resources/goldstandard_insilico100_multifactorial_5.csv
cdt/independence/__init__.py
cdt/independence/graph/FSGNN.py
cdt-0.6.0.dist-info/LICENSE.md
cdt-0.6.0.dist-info/METADATA
cdt-0.6.0.dist-info/WHEEL
cdt-0.6.0.dist-info/top_level.txt
cdt-0.6.0.dist-info/RECORD
