Metadata-Version: 2.1
Name: cdt
Version: 0.6.0
Summary: A Toolbox for causal graph inference
Home-page: https://github.com/FenTechSolutions/CausalDiscoveryToolbox
Author: Diviyan Kalainathan
Author-email: diviyan.kalainathan@lri.fr
License: Apache 2.0
Platform: UNKNOWN
License-File: LICENSE.md
